fastlz.cpython-314-darwin.so
pyfastlz_infernitydev-0.0.3.dist-info/RECORD
pyfastlz_infernitydev-0.0.3.dist-info/WHEEL
pyfastlz_infernitydev-0.0.3.dist-info/top_level.txt
pyfastlz_infernitydev-0.0.3.dist-info/METADATA
