Metadata-Version: 2.4
Name: pyfastlz-infernitydev
Version: 0.0.3
Summary: An extended wrapper for FastLZ which takes in and returns the length seperately, instead of in the bytes field
Home-page: https://github.com/infernitydev/pyfastlz-infernitydev
Author: 'Jared Suttles, Paul Chan, whirlingstars'
License: BSD License
Classifier: Development Status :: 4 - Beta
Classifier: Intended Audience :: Developers
Classifier: Operating System :: POSIX
Classifier: Programming Language :: C
Classifier: Programming Language :: Python
Classifier: Topic :: Software Development :: Libraries
Classifier: Topic :: System :: Archiving :: Compression
Classifier: Topic :: Utilities
Requires-Python: >=3.9
Provides-Extra: dev
Requires-Dist: pytest; extra == "dev"
Dynamic: description
Dynamic: description-content-type
